cobblr/__init__.py
cobblr/cobblr.py
cobblr/cobblr_debug.py
cobblr/cobblr_static_functions.py
cobblr/config.py
cobblr/Routines/CobblrDealer.py
cobblr/Routines/CobblrHandler.py
cobblr/Routines/CobblrHeartbeat.py
cobblr/Routines/CobblrPubSubProxy.py
cobblr/Routines/CobblrPublish.py
cobblr/Routines/CobblrRouter.py
cobblr/Routines/CobblrRoutine.py
cobblr/Routines/CobblrSubscribe.py
cobblr/Routines/__init__.py
cobblr-0.1.4.dist-info/LICENCE
cobblr-0.1.4.dist-info/METADATA
cobblr-0.1.4.dist-info/WHEEL
cobblr-0.1.4.dist-info/top_level.txt
cobblr-0.1.4.dist-info/RECORD
