Metadata-Version: 2.1
Name: cobblr
Version: 0.1.4
Summary: pyzmq broker and client handlers with name based addressing
Home-page: https://github.com/Iotamike/cobblr
Author: Michael McNally
Author-email: dr.michael.j.mcnally@gmail.com
License: UNKNOWN
Project-URL: Bug Tracker, https://github.com/Iotamike/cobblr/issues
Platform: UNKNOWN
Classifier: Programming Language :: Python :: 3
Classifier: License :: OSI Approved :: GNU General Public License v3 (GPLv3)
Classifier: Operating System :: Microsoft :: Windows :: Windows 10
Classifier: Operating System :: POSIX :: Linux
Classifier: Topic :: Communications
Requires-Python: >=3.9
License-File: LICENCE
